CHANGELOG.txt
LICENSE.txt
MANIFEST.in
README.md
setup.cfg
setup.py
TOPSIS_GIRIK.egg-info/SOURCES.txt
TOPSIS_GIRIK.egg-info/dependency_links.txt
TOPSIS_GIRIK.egg-info/requires.txt
TOPSIS_GIRIK.egg-info/top_level.txt
TOPSIS_GIRIK_102003178.egg-info/PKG-INFO
TOPSIS_GIRIK_102003178.egg-info/SOURCES.txt
TOPSIS_GIRIK_102003178.egg-info/dependency_links.txt
TOPSIS_GIRIK_102003178.egg-info/entry_points.txt
TOPSIS_GIRIK_102003178.egg-info/requires.txt
TOPSIS_GIRIK_102003178.egg-info/top_level.txt
topsis_10191117pip_yash-1.0.0/topsis_10191117pip_yash-1.0.0/setup.py
topsis_10191117pip_yash-1.0.0/topsis_10191117pip_yash-1.0.0/topsis_10191117pip_yash.egg-info/SOURCES.txt
topsis_10191117pip_yash-1.0.0/topsis_10191117pip_yash-1.0.0/topsis_10191117pip_yash.egg-info/dependency_links.txt
topsis_10191117pip_yash-1.0.0/topsis_10191117pip_yash-1.0.0/topsis_10191117pip_yash.egg-info/entry_points.txt
topsis_10191117pip_yash-1.0.0/topsis_10191117pip_yash-1.0.0/topsis_10191117pip_yash.egg-info/requires.txt
topsis_10191117pip_yash-1.0.0/topsis_10191117pip_yash-1.0.0/topsis_10191117pip_yash.egg-info/top_level.txt
topsis_10191117pip_yash-1.0.0/topsis_10191117pip_yash-1.0.0/topsis_python/topsis.py
topsis_python/topsis.py