Metadata-Version: 2.1
Name: TOPSIS-GIRIK-102003178
Version: 1.3.6
Summary: A Python package to find TOPSIS for multi-criteria decision analysis method
Home-page: https://www.github.com/girikgarg8
Author: Girik Garg
Author-email: girikgarg8@gmail.com
License: MIT
Keywords: topsis,UCS654,TIET
Classifier: Development Status :: 3 - Alpha
Classifier: Intended Audience :: Developers
Classifier: Operating System :: Microsoft :: Windows :: Windows 10
Classifier: License :: OSI Approved :: MIT License
Classifier: Programming Language :: Python :: 3
License-File: LICENSE.txt
